{
  "schema_version": "1.0.0",
  "generator_version": "0.1.1",
  "issue_id": "tldr-marketing:2025-06-03",
  "sector": "TLDR Marketing",
  "sector_slug": "tldr-marketing",
  "date": "2025-06-03",
  "source_path": "TLDR Marketing/article_03-06-2025.md",
  "source_content_hash": "sha256:3e70c446531f01b0981120ef5e339f3bb4a0dc862c9aee5f325f2f185366a857",
  "format_family": "links_block",
  "parse_status": "complete",
  "parse_warnings": [
    {
      "code": "footer_truncated",
      "message": "Subscription/account footer truncated before parse",
      "line": null
    }
  ],
  "title": "TLDR MARKETING 2025-06-03",
  "sections": [
    {
      "id": "general",
      "heading": "GENERAL",
      "order": 1,
      "articles": [
        {
          "id": "tldr-marketing:2025-06-03:a04",
          "order": 1,
          "title": "",
          "summary": "Delve ran 4 placements across 2 TLDR newsletters and brought in 66 leads, with a meaningful chunk from enterprise. The result: $1M in attributed pipeline and a 52x ROI.",
          "url": "https://advertise.tldr.tech/case-studies/delve-drives-1m-in-attributed-pipeline-52x-roi-through-tldr-ads/?utm_source=tldrmarketing&utm_medium=newsletter&utm_campaign=primary06032025",
          "reading_time_minutes": null,
          "source_domain": "advertise.tldr.tech",
          "content_type": "sponsor",
          "is_sponsor": true
        },
        {
          "id": "tldr-marketing:2025-06-03:a04",
          "order": 2,
          "title": "Read the Delve case study.",
          "summary": "",
          "url": "https://advertise.tldr.tech/case-studies/delve-drives-1m-in-attributed-pipeline-52x-roi-through-tldr-ads/?utm_source=tldrmarketing&utm_medium=newsletter&utm_campaign=primary06032025",
          "reading_time_minutes": null,
          "source_domain": "advertise.tldr.tech",
          "content_type": "editorial",
          "is_sponsor": false
        }
      ]
    },
    {
      "id": "news-trends",
      "heading": "NEWS & TRENDS",
      "order": 2,
      "articles": [
        {
          "id": "tldr-marketing:2025-06-03:a05",
          "order": 1,
          "title": "META AIMS TO FULLY AUTOMATE ADVERTISING WITH AI BY 2026",
          "summary": "Meta plans to automate ad creation and targeting with AI by the end of 2026. Brands will only need to provide a product image and budget, and Meta's AI will generate the ad content, suggest spend, and determine targeting across Facebook and Instagram. The platform will also offer real-time ad personalization based on factors like location.",
          "url": "https://links.tldrnewsletter.com/w045oK",
          "reading_time_minutes": 2,
          "source_domain": "links.tldrnewsletter.com",
          "content_type": "editorial",
          "is_sponsor": false
        },
        {
          "id": "tldr-marketing:2025-06-03:a06",
          "order": 2,
          "title": "BLUESKY HAS CAUGHT ON WITH MANY NEWS INFLUENCERS, BUT X REMAINS POPULAR",
          "summary": "Bluesky saw a sharp rise in adoption by news influencers after the 2024 election. The platform's growth is driven largely by left-leaning influencers, 69% of whom now have a Bluesky account, compared to just 15% of right-leaning ones. Despite Bluesky's rise, X remains dominant, with 82% of the influencers still using it and 83% of those posting there 4 or more days a week. In contrast, only 31% of Bluesky users posted that often in early 2025, and 48% posted irregularly or not at all. Most influencers on Bluesky also maintain an X account and few have left X entirely.",
          "url": "https://www.pewresearch.org/short-reads/2025/05/29/bluesky-has-caught-on-with-many-news-influencers-but-x-remains-popular/?utm_source=tldrmarketing",
          "reading_time_minutes": 5,
          "source_domain": "pewresearch.org",
          "content_type": "editorial",
          "is_sponsor": false
        }
      ]
    },
    {
      "id": "strategies-tactics",
      "heading": "STRATEGIES & TACTICS",
      "order": 3,
      "articles": [
        {
          "id": "tldr-marketing:2025-06-03:a07",
          "order": 1,
          "title": "COPYWRITING: WORKING HARD VS. HARDLY WORKING",
          "summary": "Lead generation should prioritize quality over quantity. For broad appeal, attract a wide group through multiple channels and incentives, such as charity runs that engage hundreds of millions of runners worldwide. For niche segments, use insider language to build a strong connection with a specific group, like campaigns aimed at dedicated running enthusiasts. For the most exclusive approach, avoid promotion altogether to create intrigue and status.",
          "url": "https://conversion-rate-experts.com/copywriting-friday-working-hard-vs-hardly-working/?utm_source=tldrmarketing",
          "reading_time_minutes": 5,
          "source_domain": "conversion-rate-experts.com",
          "content_type": "editorial",
          "is_sponsor": false
        },
        {
          "id": "tldr-marketing:2025-06-03:a08",
          "order": 2,
          "title": "CROSS-SELL TACTICS OF TOP DTC BRANDS",
          "summary": "Product bundling groups related items at a discount to encourage larger purchases and reduce decision fatigue. Shopping cart and checkout suggestions surface add-ons when shoppers are already in buying mode. Threshold-based incentives, such as free gifts or shipping when spending reaches a certain amount, drive higher-value orders.",
          "url": "https://www.practicalecommerce.com/cross-sell-tactics-of-top-dtc-brands?utm_source=tldrmarketing",
          "reading_time_minutes": 3,
          "source_domain": "practicalecommerce.com",
          "content_type": "editorial",
          "is_sponsor": false
        }
      ]
    },
    {
      "id": "resources-tools",
      "heading": "RESOURCES & TOOLS",
      "order": 4,
      "articles": [
        {
          "id": "tldr-marketing:2025-06-03:a09",
          "order": 1,
          "title": "INSTAGRAM CREATORS WITH OVER 100K FOLLOWERS WILL GET ACCESS TO ADDITIONAL COMMENT FILTERS",
          "summary": "Instagram is expanding its comment filtering tools to creators with over 100K followers. These tools let users sort comments by top engagement, newest first, or commenter follower count. Creators can also filter to show comments only from people they follow, verified users, or subscribers. These features help large creators focus on key interactions and boost engagement.",
          "url": "https://www.socialmediatoday.com/news/instagram-adds-comment-filters-for-accounts-100k-followers/749504/?utm_source=tldrmarketing",
          "reading_time_minutes": 2,
          "source_domain": "socialmediatoday.com",
          "content_type": "editorial",
          "is_sponsor": false
        },
        {
          "id": "tldr-marketing:2025-06-03:a10",
          "order": 2,
          "title": "THE RISE OF B2B INFLUENCE: HOW CREATORS ARE INFLUENCING BUYERS",
          "summary": "B2B buyers purposefully integrate influencer content into every major step of the purchasing journey. LinkedIn's recent guide outlines that credibility and subject-matter expertise are more effective in converting leads than broad appeal in B2B creator partnerships. It also highlights that video leads all other formats in engagement and performance.",
          "url": "https://www.linkedin.com/business/marketing/blog/linkedin-ads/b2b-creator-marketing-linkedin?utm_source=tldrmarketing",
          "reading_time_minutes": 3,
          "source_domain": "linkedin.com",
          "content_type": "editorial",
          "is_sponsor": false
        }
      ]
    },
    {
      "id": "miscellaneous",
      "heading": "MISCELLANEOUS",
      "order": 5,
      "articles": [
        {
          "id": "tldr-marketing:2025-06-03:a11",
          "order": 1,
          "title": "ORGANIC POSTS AND BRAND-VOICE TESTS: HOW ADVERTISERS ARE APPROACHING THREADS",
          "summary": "Threads now has over 350M monthly active users and is available to all advertisers, but most brands remain in early testing phases. Media buyers see it less as a place to drive conversions and more as a platform to explore brand voice and tone through organic posts. Limited standalone ad options and uncertainty around platform strategy are keeping investment conservative for now.",
          "url": "https://links.tldrnewsletter.com/YWNOvf",
          "reading_time_minutes": 3,
          "source_domain": "links.tldrnewsletter.com",
          "content_type": "editorial",
          "is_sponsor": false
        },
        {
          "id": "tldr-marketing:2025-06-03:a12",
          "order": 2,
          "title": "LEAH'S LEADERSHIP GUIDE - PART 5: EXPERIMENTATION CULTURE",
          "summary": "Strong leadership requires fostering a culture where failure is embraced as a path to learning, not just tolerated. Over 60% of experiments in a typical B2B SaaS setting fail, so leaders must set clear, early expectations that define success by learning, not just positive outcomes. To keep morale high, leaders should balance big, risky goals with achievable wins using a 70-20-10 mix of safe bets, incremental gains, and moonshots. Risk conversations must be ongoing, and leaders need to model vulnerability and failure openly to earn trust. Organizing learnings in accessible, well-maintained repositories ensures insights from failures are retained and used.",
          "url": "https://www.leahtharin.com/p/leahs-leadership-guide-part-5-experimentation?utm_source=tldrmarketing",
          "reading_time_minutes": 7,
          "source_domain": "leahtharin.com",
          "content_type": "editorial",
          "is_sponsor": false
        }
      ]
    },
    {
      "id": "quick-links",
      "heading": "QUICK LINKS",
      "order": 6,
      "articles": [
        {
          "id": "tldr-marketing:2025-06-03:a13",
          "order": 1,
          "title": "PAIN IS THE PITCH",
          "summary": "Try stating the problem as a question in your next sales page headline.",
          "url": "https://microcopyexamples.substack.com/p/pain-is-the-pitch?utm_source=tldrmarketing",
          "reading_time_minutes": 1,
          "source_domain": "microcopyexamples.substack.com",
          "content_type": "editorial",
          "is_sponsor": false
        },
        {
          "id": "tldr-marketing:2025-06-03:a14",
          "order": 2,
          "title": "THE RECENT HISTORY OF AI IN 32 OTTERS",
          "summary": "AI-generated media will soon be indistinguishable from reality, widely accessible, and difficult to regulate.",
          "url": "https://www.oneusefulthing.org/p/the-recent-history-of-ai-in-32-otters?utm_source=tldrmarketing",
          "reading_time_minutes": 6,
          "source_domain": "oneusefulthing.org",
          "content_type": "editorial",
          "is_sponsor": false
        },
        {
          "id": "tldr-marketing:2025-06-03:a15",
          "order": 3,
          "title": "YOU NEED MINDSHARE. NOT INTENT. WHY?",
          "summary": "Building brand and mindshare builds trust and makes buyers more likely to choose you when the time comes.",
          "url": "https://www.linkedin.com/posts/palashsoni_why-mindshare-wins-in-b2b-ugcPost-7335301064918814720-x9Rw?utm_source=tldrmarketing",
          "reading_time_minutes": 2,
          "source_domain": "linkedin.com",
          "content_type": "editorial",
          "is_sponsor": false
        }
      ]
    }
  ]
}
