{
  "schema_version": "1.0.0",
  "generator_version": "0.1.3",
  "issue_id": "tldr-product:2024-11-01",
  "sector": "TLDR Product",
  "sector_slug": "tldr-product",
  "date": "2024-11-01",
  "source_path": "TLDR Product/article_01-11-2024.md",
  "source_content_hash": "sha256:9c78c8ba93cefde6befe7e86d6c7cc9b7bccb5150b8707a94358ad5c6de5c928",
  "format_family": "links_block",
  "parse_status": "complete",
  "parse_warnings": [
    {
      "code": "footer_truncated",
      "message": "Subscription/account footer truncated before parse",
      "line": null
    }
  ],
  "title": "TLDR PRODUCT MANAGEMENT 2024-11-01",
  "sections": [
    {
      "id": "general",
      "heading": "GENERAL",
      "order": 1,
      "articles": [
        {
          "id": "tldr-product:2024-11-01:a04",
          "order": 1,
          "title": "THE STATE OF DIGITAL ASSET MANAGEMENT",
          "summary": "Visual content is vital for any business — as is the speed with which brands can find, manage, transform, and deliver that content. Is today's digital asset management (DAM) up to the task?",
          "url": "https://cloudinary.com/products/digital_asset_management/survey?utm_source=tldr-pmm-nl&utm_medium=sponsored_placement&utm_campaign=4034&utm_term=dam-survey&utm_content=newsletter",
          "reading_time_minutes": null,
          "source_domain": "cloudinary.com",
          "content_type": "sponsor",
          "is_sponsor": true
        },
        {
          "id": "tldr-product:2024-11-01:a04",
          "order": 2,
          "title": "driving priorities. Read the results here →",
          "summary": "> Is better DAM around the corner? In next week's webinar, Cloudinary will introduce Assets, the API-first DAM platform that streamlines every stage of the asset lifecycle — from creative review to",
          "url": "https://cloudinary.com/products/digital_asset_management/survey?utm_source=tldr-pmm-nl&utm_medium=sponsored_placement&utm_campaign=4034&utm_term=dam-survey&utm_content=newsletter",
          "reading_time_minutes": null,
          "source_domain": "cloudinary.com",
          "content_type": "editorial",
          "is_sponsor": false
        },
        {
          "id": "tldr-product:2024-11-01:a05",
          "order": 3,
          "title": "AI-powered image editing. Register to join live →",
          "summary": "",
          "url": "https://lp.cloudinary.com/wnr.lp.new-dam-era-4030.html?utm_source=tldr-pmm-nl&utm_medium=sponsored_placement&utm_campaign=4034&utm_term=dam-product-webinar&utm_content=newsletter",
          "reading_time_minutes": null,
          "source_domain": "lp.cloudinary.com",
          "content_type": "editorial",
          "is_sponsor": false
        }
      ]
    },
    {
      "id": "news-trends",
      "heading": "NEWS & TRENDS",
      "order": 2,
      "articles": [
        {
          "id": "tldr-product:2024-11-01:a06",
          "order": 1,
          "title": "AI IS EATING JOURNALISM, EDUCATION, AND CREATIVES",
          "summary": "",
          "url": "https://hackernoon.com/ai-is-eating-journalism-education-and-creatives?utm_source=tldrproduct",
          "reading_time_minutes": 5,
          "source_domain": "hackernoon.com",
          "content_type": "editorial",
          "is_sponsor": false
        },
        {
          "id": "tldr-product:2024-11-01:a07",
          "order": 2,
          "title": "META'S AI ABUNDANCE",
          "summary": "Meta is well-positioned to thrive amid digital advertising challenges and AI advancements. It could leverage generative AI to boost ad effectiveness while enhancing margin through black-box ad delivery. In the long term, Meta's use of generative UI and augmented reality could redefine digital interactions, turning every digital and physical space into potential ad space.",
          "url": "https://stratechery.com/2024/metas-ai-abundance/?utm_source=tldrproduct",
          "reading_time_minutes": 18,
          "source_domain": "stratechery.com",
          "content_type": "editorial",
          "is_sponsor": false
        },
        {
          "id": "tldr-product:2024-11-01:a08",
          "order": 3,
          "title": "TRANSFORMATION AS A PROJECT",
          "summary": "Adopting a prototyping or pilot team approach in transformation may seem time-consuming, but in product development, it often accelerates successful outcomes. Using the product model can boost your chances of a successful transformation, helping your company achieve its goals more efficiently.",
          "url": "https://www.svpg.com/transformation-as-a-project/?utm_source=tldrproduct",
          "reading_time_minutes": 4,
          "source_domain": "svpg.com",
          "content_type": "editorial",
          "is_sponsor": false
        }
      ]
    },
    {
      "id": "opinions-tutorials",
      "heading": "OPINIONS & TUTORIALS",
      "order": 3,
      "articles": [
        {
          "id": "tldr-product:2024-11-01:a09",
          "order": 1,
          "title": "DON'T BE EVIL",
          "summary": "Google's delayed perception as \"evil\" reflected both the company's initial benevolence and the privilege of being profitable enough to avoid ethical compromises. Ambitious companies often need exceptional success to maintain their ideals and, lacking this, face pressure to compromise values for survival. Google served as an exception to the rule.",
          "url": "https://benn.substack.com/p/dont-be-evil?utm_source=tldrproduct",
          "reading_time_minutes": 6,
          "source_domain": "benn.substack.com",
          "content_type": "editorial",
          "is_sponsor": false
        },
        {
          "id": "tldr-product:2024-11-01:a10",
          "order": 2,
          "title": "PRODUCT DISCOVERY ACTIVITIES BY RISK",
          "summary": "This guide to product discovery outlines different activities categorized by risk (viability, desirability, feasibility, and usability) to help teams de-risk their product development by identifying and testing core assumptions. Take action over waiting for perfect data - start with customer interviews, prototyping, or data collection.",
          "url": "https://www.antmurphy.me/newsletter/product-discovery-activities-by-risk?utm_source=tldrproduct",
          "reading_time_minutes": 5,
          "source_domain": "antmurphy.me",
          "content_type": "editorial",
          "is_sponsor": false
        },
        {
          "id": "tldr-product:2024-11-01:a11",
          "order": 3,
          "title": "GUIDE, DON'T COMMAND.",
          "summary": "Collaborating with a language model feels more like guiding a creative partner than issuing commands. To foster effective output, it's essential to provide context, discuss high-level concepts, and create a structured process rather than dictating specifics. This meta-approach requires thinking about prompting itself, not just individual instructions.",
          "url": "https://www.unknownarts.co/p/guide-dont-command?utm_source=tldrproduct",
          "reading_time_minutes": 6,
          "source_domain": "unknownarts.co",
          "content_type": "editorial",
          "is_sponsor": false
        }
      ]
    },
    {
      "id": "resources-tools",
      "heading": "RESOURCES & TOOLS",
      "order": 4,
      "articles": [
        {
          "id": "tldr-product:2024-11-01:a12",
          "order": 1,
          "title": "INTERESTED IN SOFTWARE-LED PAYMENTS? THIS GUIDE WILL HELP YOU SELECT THE BEST PARTNER FOR YOUR PLATFORM.",
          "summary": "In an extremely competitive market, software-led payments can help you differentiate your platform, deliver optimal experiences, and drive customer loyalty. But success with payments hinges on one very important piece: your payments partnership. Use this free buyer's guide and evaluation tool to help you choose the best possible partner for your company (or determine if it's time to make a switch).",
          "url": "https://www.payrix.com/resources/ebook/buyers-guide?utm_source=tldr&utm_medium=sponsored-content&utm_campaign=2024-buyers-guide",
          "reading_time_minutes": null,
          "source_domain": "payrix.com",
          "content_type": "sponsor",
          "is_sponsor": true
        },
        {
          "id": "tldr-product:2024-11-01:a12",
          "order": 2,
          "title": "Download Guide",
          "summary": "",
          "url": "https://www.payrix.com/resources/ebook/buyers-guide?utm_source=tldr&utm_medium=sponsored-content&utm_campaign=2024-buyers-guide",
          "reading_time_minutes": null,
          "source_domain": "payrix.com",
          "content_type": "editorial",
          "is_sponsor": false
        },
        {
          "id": "tldr-product:2024-11-01:a13",
          "order": 3,
          "title": "DOUBLE DIAMOND DESIGN PROCESS AND ITS VARIATIONS",
          "summary": "",
          "url": "https://links.tldrnewsletter.com/JaU4Xj",
          "reading_time_minutes": 3,
          "source_domain": "links.tldrnewsletter.com",
          "content_type": "editorial",
          "is_sponsor": false
        },
        {
          "id": "tldr-product:2024-11-01:a14",
          "order": 4,
          "title": "FREEMIUM VS FREE TRIAL: WHICH IS RIGHT FOR YOU",
          "summary": "Freemium and free trials both support product-led growth, allowing products to drive sales. Freemium works well for building long-term engagement and gradually showcasing value, while a time-limited free trial suits products that offer instant value and aim for quick conversions. The choice depends on the product's nature and desired engagement approach.",
          "url": "https://www.prodpad.com/blog/freemium-vs-free-trial/?utm_source=tldrproduct",
          "reading_time_minutes": 19,
          "source_domain": "prodpad.com",
          "content_type": "editorial",
          "is_sponsor": false
        }
      ]
    },
    {
      "id": "miscellaneous",
      "heading": "MISCELLANEOUS",
      "order": 5,
      "articles": [
        {
          "id": "tldr-product:2024-11-01:a15",
          "order": 1,
          "title": "YOU HAVE YOUR WHOLE LIFE TO WRITE YOUR FIRST RECORD, AND ONLY 12 MONTHS TO WRITE YOUR SECOND",
          "summary": "SaaS companies, like musicians, face intense pressure to follow a successful debut with a second product that resonates and grows their customer base, especially around the Series B and C stages. To avoid a \"sophomore slump,\" companies should expand meaningfully on their original success, align with core users, and release at the right time without diluting their brand, creating a second hit product that builds trust and deepens customer relationships.",
          "url": "https://www.mostlymetrics.com/p/you-have-your-whole-life-to-write?utm_source=tldrproduct",
          "reading_time_minutes": 6,
          "source_domain": "mostlymetrics.com",
          "content_type": "editorial",
          "is_sponsor": false
        },
        {
          "id": "tldr-product:2024-11-01:a16",
          "order": 2,
          "title": "WHEN YOU'RE PIGEONHOLED AS “GREAT AT PROJECT MANAGEMENT”",
          "summary": "Project management skills are often undervalued in the workplace and associated with junior roles, which can limit how others perceive an individual's contributions, even if they perform strategic work. To counteract this, employees should intentionally use strategic language to frame their roles and highlight their broader impact, positioning themselves beyond mere execution.",
          "url": "https://newsletter.weskao.com/p/pigeonholed-project-management?utm_source=tldrproduct",
          "reading_time_minutes": 9,
          "source_domain": "newsletter.weskao.com",
          "content_type": "editorial",
          "is_sponsor": false
        }
      ]
    },
    {
      "id": "quick-links",
      "heading": "QUICK LINKS",
      "order": 6,
      "articles": [
        {
          "id": "tldr-product:2024-11-01:a17",
          "order": 1,
          "title": "THE ANATOMY OF NETWORKING",
          "summary": "Networking is best done proactively while employed.",
          "url": "https://www.linkedin.com/posts/aatirar_i-asked-a-few-folks-how-they-network-their-activity-7257017098428628992-mwlm?utm_source=tldrproduct",
          "reading_time_minutes": 2,
          "source_domain": "linkedin.com",
          "content_type": "editorial",
          "is_sponsor": false
        },
        {
          "id": "tldr-product:2024-11-01:a18",
          "order": 2,
          "title": "AI PROMPT CHEATSHEET",
          "summary": "A cheat sheet of five proven prompt engineering techniques (plus advanced tips) to help you get precise results from AI.",
          "url": "https://threadreaderapp.com/thread/1851297976372904106.html?utm_source=tldrproduct",
          "reading_time_minutes": 2,
          "source_domain": "threadreaderapp.com",
          "content_type": "editorial",
          "is_sponsor": false
        }
      ]
    }
  ]
}
