{
  "schema_version": "1.0.0",
  "generator_version": "0.1.3",
  "issue_id": "tldr-cybersecurity:2023-08-14",
  "sector": "TLDR Cybersecurity",
  "sector_slug": "tldr-cybersecurity",
  "date": "2023-08-14",
  "source_path": "TLDR Cybersecurity/article_14-08-2023.md",
  "source_content_hash": "sha256:89889bee51447084d836ce67ab493a31aa52c1071325051231c7a7f23666b890",
  "format_family": "inline_url",
  "parse_status": "complete",
  "parse_warnings": [
    {
      "code": "footer_truncated",
      "message": "Subscription/account footer truncated before parse",
      "line": null
    }
  ],
  "title": "TLDR CYBERSECURITY 2023-08-14",
  "sections": [
    {
      "id": "attacks-vulnerabilities",
      "heading": "ATTACKS & VULNERABILITIES",
      "order": 1,
      "articles": []
    },
    {
      "id": "strategies-tactics",
      "heading": "STRATEGIES & TACTICS",
      "order": 2,
      "articles": []
    },
    {
      "id": "launches-tools",
      "heading": "LAUNCHES & TOOLS",
      "order": 3,
      "articles": [
        {
          "id": "tldr-cybersecurity:2023-08-14:o001",
          "order": 1,
          "title": "WEB-CHECK",
          "summary": "Get an insight into the inner-workings of a given website: uncover potential attack vectors, analyze server architecture, view security configurations, and learn what technologies a site is using.",
          "url": "https://github.com/Lissy93/web-check?utm_source=tldrcybersecurity",
          "reading_time_minutes": null,
          "source_domain": "github.com",
          "content_type": "github_repo",
          "is_sponsor": false
        },
        {
          "id": "tldr-cybersecurity:2023-08-14:o002",
          "order": 2,
          "title": "KUBEFUZZ",
          "summary": "kubefuzz is a generative and mutative fuzzer for liberating admissions controller chains that works by parsing the cluster API specification. Users can supply constraints to guide the fuzzer’s resource generation.",
          "url": "https://github.com/avolens/kubefuzz?utm_source=tldrcybersecurity",
          "reading_time_minutes": null,
          "source_domain": "github.com",
          "content_type": "github_repo",
          "is_sponsor": false
        }
      ]
    },
    {
      "id": "miscellaneous",
      "heading": "MISCELLANEOUS",
      "order": 4,
      "articles": [
        {
          "id": "tldr-cybersecurity:2023-08-14:o003",
          "order": 1,
          "title": "BLACK HAT USA 2023 SLIDES",
          "summary": "Here are all the slides presented at Black Hat USA 2023.",
          "url": "https://github.com/onhexgroup/Conferences/tree/main/Black%20Hat%20USA%202023%20slides?utm_source=tldrcybersecurity",
          "reading_time_minutes": null,
          "source_domain": "github.com",
          "content_type": "github_repo",
          "is_sponsor": false
        }
      ]
    },
    {
      "id": "quick-links",
      "heading": "QUICK LINKS",
      "order": 5,
      "articles": [
        {
          "id": "tldr-cybersecurity:2023-08-14:o004",
          "order": 1,
          "title": "INTRODUCING THE FIRST AWS SECURITY HEROES",
          "summary": "The AWS Heroes program recognizes community members that have combined technical expertise and a desire to help the community. AWS has now created a specialized category for Security Heroes.",
          "url": "https://aws.amazon.com/blogs/aws/introducing-the-first-aws-security-heroes/?utm_source=tldrcybersecurity",
          "reading_time_minutes": 1,
          "source_domain": "aws.amazon.com",
          "content_type": "editorial",
          "is_sponsor": false
        }
      ]
    }
  ]
}
