{
  "schema_version": "1.0.0",
  "generator_version": "0.1.1",
  "issue_id": "tldr-marketing:2023-09-04",
  "sector": "TLDR Marketing",
  "sector_slug": "tldr-marketing",
  "date": "2023-09-04",
  "source_path": "TLDR Marketing/article_04-09-2023.md",
  "source_content_hash": "sha256:74199183bcea551d300289f5a5c890c3d129abb1b7bdc15dcec0d89a90a5f30a",
  "format_family": "inline_url",
  "parse_status": "complete",
  "parse_warnings": [
    {
      "code": "footer_truncated",
      "message": "Subscription/account footer truncated before parse",
      "line": null
    }
  ],
  "title": "TLDR MARKETING 2023-09-04",
  "sections": [
    {
      "id": "news-trends",
      "heading": "NEWS & TRENDS",
      "order": 1,
      "articles": [
        {
          "id": "tldr-marketing:2023-09-04:o001",
          "order": 1,
          "title": "FROM SUBSCRIBERS",
          "summary": "X is working to implement direct contact sharing, which would benefit creators and brands looking to engage with their audiences outside the platform. Based on the report, a new checkbox would be added to the subscribe pop-up window asking the subscriber if they want to share their personal email.",
          "url": "https://www.socialmediatoday.com/news/x-tests-new-option-that-would-enable-creators-to-gather-email-contacts-from/692647/?utm_source=tldrmarketing",
          "reading_time_minutes": 3,
          "source_domain": "socialmediatoday.com",
          "content_type": "editorial",
          "is_sponsor": false
        },
        {
          "id": "tldr-marketing:2023-09-04:o002",
          "order": 2,
          "title": "‘SUNSET’",
          "summary": "Google’s Universal Analytics was supposed to stop processing data on July 1, but many marketers still see new data flowing in today. GA4 is UA’s replacement. As tempting as it may be, it would be unwise to rely on UA for analytics purposes as it could stop processing data at any minute.",
          "url": "https://searchengineland.com/universal-analytics-processing-data-one-month-on-430025?utm_source=tldrmarketing",
          "reading_time_minutes": 4,
          "source_domain": "searchengineland.com",
          "content_type": "editorial",
          "is_sponsor": false
        }
      ]
    },
    {
      "id": "strategies-tactics",
      "heading": "STRATEGIES & TACTICS",
      "order": 2,
      "articles": [
        {
          "id": "tldr-marketing:2023-09-04:o003",
          "order": 1,
          "title": "3 COPYWRITING EXERCISES TO WRITE COPY THAT SELLS",
          "summary": "Copy is fundamental to marketing and growth — but so often overlooked. This guide contains 3 exercises to make your copy more effective: removing “we” statements, in-depth customer storytelling, and addressing customer objections.",
          "url": "https://news.marketingpowerups.com/p/sarah-stockdale-copywriting-exercises?utm_source=tldrmarketing",
          "reading_time_minutes": 4,
          "source_domain": "news.marketingpowerups.com",
          "content_type": "editorial",
          "is_sponsor": false
        },
        {
          "id": "tldr-marketing:2023-09-04:o004",
          "order": 2,
          "title": "HOW TO CRAFT AN IMPECCABLE GO TO MARKET STRATEGY",
          "summary": "Having a go-to-market strategy is important to successfully launch a product or service. This article highlights different types of strategies, steps to create one, best practices, and success stories from Slack and Fitbit.",
          "url": "https://neilpatel.com/blog/go-to-market-strategy/?utm_source=tldrmarketing",
          "reading_time_minutes": 8,
          "source_domain": "neilpatel.com",
          "content_type": "editorial",
          "is_sponsor": false
        }
      ]
    },
    {
      "id": "resources-tools",
      "heading": "RESOURCES & TOOLS",
      "order": 3,
      "articles": [
        {
          "id": "tldr-marketing:2023-09-04:o005",
          "order": 1,
          "title": "SCHEMA MARKUP: WHAT IT IS & HOW TO IMPLEMENT IT",
          "summary": "Schema markup is structured code that helps search engines understand the information on a page. Google can use it to show rich results, which can earn a page more clicks. Schema types include Article, Breadcrumb, Product, plus many more.",
          "url": "https://ahrefs.com/blog/schema-markup/?utm_source=tldrmarketing",
          "reading_time_minutes": 9,
          "source_domain": "ahrefs.com",
          "content_type": "editorial",
          "is_sponsor": false
        }
      ]
    },
    {
      "id": "miscellaneous",
      "heading": "MISCELLANEOUS",
      "order": 4,
      "articles": [
        {
          "id": "tldr-marketing:2023-09-04:o006",
          "order": 1,
          "title": "HOW DID CLICKUP BECOME A $150M REVENUE MACHINE?",
          "summary": "Since launching in 2017, Clickup has grown rapidly and reached a customer base of 85K. They made this possible with a rigorous product and marketing strategy. Its tactics included conversion-focused content marketing, daily blog posts for SEO, community engagement, customer referrals, and “purple cow” advertising.",
          "url": "https://aatir.substack.com/p/how-did-clickup-become-a-150m-revenue?utm_source=tldrmarekting",
          "reading_time_minutes": 8,
          "source_domain": "aatir.substack.com",
          "content_type": "editorial",
          "is_sponsor": false
        },
        {
          "id": "tldr-marketing:2023-09-04:o007",
          "order": 2,
          "title": "WHEN CUSTOMERS CARE ABOUT QUALITY BUT JUST NOT YET",
          "summary": "Assembly quality was assumed to be a necessity for car sales, yet Tesla succeeded while delivering cars with issues. This illustrates the effectiveness of the brand’s positioning, as well as the importance of understanding what a brand actually competes against. Tesla’s product isn’t just a vehicle to get you from point A to point B, but rather a set of exclusive features that no other car brand offers.",
          "url": "https://www.leahtharin.com/p/when-customers-care-about-quality?utm_source=tldrmarketing",
          "reading_time_minutes": 7,
          "source_domain": "leahtharin.com",
          "content_type": "editorial",
          "is_sponsor": false
        },
        {
          "id": "tldr-marketing:2023-09-04:o008",
          "order": 3,
          "title": "DECENTRALIZED MEDIA FOR CREATORS: THE RUG RADIO STORY",
          "summary": "Web3 is transforming how creators engage with their followers by empowering them to directly own and monetize their audiences. Different from traditional platforms, decentralized autonomous organizations (DAO) like 'Rug Radio' are owned and operated by creators and fans. Decisions are voted by all token holders and the organization has its own treasury with proceeds from NFT sales.",
          "url": "https://www.socialmediaexaminer.com/decentralized-media-for-creators-the-rug-radio-story/?utm_source=tldrmarketing",
          "reading_time_minutes": 6,
          "source_domain": "socialmediaexaminer.com",
          "content_type": "editorial",
          "is_sponsor": false
        }
      ]
    },
    {
      "id": "quick-links",
      "heading": "QUICK LINKS",
      "order": 5,
      "articles": [
        {
          "id": "tldr-marketing:2023-09-04:o009",
          "order": 1,
          "title": "",
          "summary": "Laguna Beach Textile Company saw a 400-500% increase in sales since the meme took off and they capitalized with paid advertising.",
          "url": "https://www.marketingbrew.com/stories/2023/08/31/how-the-brand-behind-selena-gomez-s-viral-blanket-seized-the-meme-nt/?utm_source=tldrmarketing",
          "reading_time_minutes": 5,
          "source_domain": "marketingbrew.com",
          "content_type": "editorial",
          "is_sponsor": false
        },
        {
          "id": "tldr-marketing:2023-09-04:o010",
          "order": 2,
          "title": "PLAN",
          "summary": "The campaign centers on four core areas: making fashion accessible, offering a compelling loyalty program, supporting varied local and cultural communities, and reinforcing a commitment to positive change.",
          "url": "https://www.marketingdive.com/news/jc-penney-turnaround-plan-inclusive-retail-marketing/692561/?utm_source=tldrmarketing",
          "reading_time_minutes": 4,
          "source_domain": "marketingdive.com",
          "content_type": "editorial",
          "is_sponsor": false
        }
      ]
    }
  ]
}
