{
  "schema_version": "1.0.0",
  "generator_version": "0.1.3",
  "issue_id": "tldr-design:2023-12-19",
  "sector": "TLDR Design",
  "sector_slug": "tldr-design",
  "date": "2023-12-19",
  "source_path": "TLDR Design/article_19-12-2023.md",
  "source_content_hash": "sha256:30f48e0304ca9e4a6d96402ec7e716d0f09ee32c5f2e063abc4fed9e046a5390",
  "format_family": "links_block",
  "parse_status": "complete",
  "parse_warnings": [
    {
      "code": "footer_truncated",
      "message": "Subscription/account footer truncated before parse",
      "line": null
    }
  ],
  "title": "TLDR DESIGN 2023-12-19",
  "sections": [
    {
      "id": "news-trends",
      "heading": "NEWS & TRENDS",
      "order": 1,
      "articles": [
        {
          "id": "tldr-design:2023-12-19:a05",
          "order": 1,
          "title": "FIGMA AND ADOBE ARE ABANDONING THEIR PROPOSED MERGER",
          "summary": "Figma and Adobe have decided to terminate their pending acquisition after 15 months of regulatory review as they no longer see a path to regulatory approval for the deal. Despite the initial goal of accelerating their contributions to their respective communities, both companies plan to continue independently and explore opportunities for user partnerships.",
          "url": "https://www.figma.com/blog/figma-adobe-abandon-proposed-merger/?utm_source=tldrdesign",
          "reading_time_minutes": 3,
          "source_domain": "figma.com",
          "content_type": "editorial",
          "is_sponsor": false
        },
        {
          "id": "tldr-design:2023-12-19:a06",
          "order": 2,
          "title": "APPLE'S GIANT CHRISTMAS BILLBOARDS DEMONSTRATE THE POWER OF ITS LOGO",
          "summary": "Giant Apple bags have become part of the landscape in cities like Los Angeles, New York, Boston, Chicago, Munich, and Paris as part of Apple's minimalist holiday campaign. 'Wonder Awaits' was designed by the tech giant's advertising agency. It features no name or copy, but the simple design leaves no doubt about who is behind the campaign.",
          "url": "https://www.creativebloq.com/news/apple-christmas-logos?utm_source=tldrdesign",
          "reading_time_minutes": 2,
          "source_domain": "creativebloq.com",
          "content_type": "editorial",
          "is_sponsor": false
        },
        {
          "id": "tldr-design:2023-12-19:a07",
          "order": 3,
          "title": "PENTAGRAM'S NEW IDENTITY FOR STEREOLABS REPOSITIONS IT FROM CAMERA BRAND TO AI LEADER",
          "summary": "The design strategically positions the symbol as a connective element that appears across the Stereolabs ecosystem, harmonizing the digital and physical aspects of the business and showcasing how design can play a transformative role in tech companies.",
          "url": "https://www.creativeboom.com/inspiration/pentagram-rebrands-stereolabs/?utm_source=tldrdesign",
          "reading_time_minutes": 5,
          "source_domain": "creativeboom.com",
          "content_type": "editorial",
          "is_sponsor": false
        }
      ]
    },
    {
      "id": "opinions-tutorials",
      "heading": "OPINIONS & TUTORIALS",
      "order": 2,
      "articles": [
        {
          "id": "tldr-design:2023-12-19:a08",
          "order": 1,
          "title": "DESIGNING PERFECT TABS",
          "summary": "When designing tabs, you should consider the context in which they manifest when choosing labels, states, icons, and orientations. It makes sense to use tabs when content is related, one level deep, and when users need to navigate between sections quickly.",
          "url": "https://uxplanet.org/designing-perfect-tabs-2c0aaf835bfc?utm_source=tldrdesign",
          "reading_time_minutes": 4,
          "source_domain": "uxplanet.org",
          "content_type": "editorial",
          "is_sponsor": false
        },
        {
          "id": "tldr-design:2023-12-19:a09",
          "order": 2,
          "title": "GENERATING PERSISTENT CHARACTERS: STILL TOO DIFFICULT",
          "summary": "Storyboards and personas benefit from depicting the same characters in various situations. Unfortunately, creating persistent characters using AI-driven image-generation tools is difficult since they are probabilistic.",
          "url": "https://jakobnielsenphd.substack.com/p/persistent-characters?utm_source=tldrdesign",
          "reading_time_minutes": 5,
          "source_domain": "jakobnielsenphd.substack.com",
          "content_type": "editorial",
          "is_sponsor": false
        },
        {
          "id": "tldr-design:2023-12-19:a10",
          "order": 3,
          "title": "INSIGHTS ARE NOT WHAT YOU THINK THEY ARE",
          "summary": "Designers and researchers who get asked “What’s the insight here?” while presenting findings from research failed at their job. This might happen because the takeaway is unclear, the other stakeholders don’t understand why, or they feel lost about what to do.",
          "url": "https://uxdesign.cc/insights-are-not-what-you-think-they-are-c7a159101a2f?utm_source=tldrdesign",
          "reading_time_minutes": 11,
          "source_domain": "uxdesign.cc",
          "content_type": "editorial",
          "is_sponsor": false
        }
      ]
    },
    {
      "id": "launches-tools",
      "heading": "LAUNCHES & TOOLS",
      "order": 3,
      "articles": [
        {
          "id": "tldr-design:2023-12-19:a11",
          "order": 1,
          "title": "A COLLECTION OF THE BEST DESIGN PRACTICES",
          "summary": "Checklist Design is a curated list of checklists for the best design practices for website pages, UI components, branding assets, and more.",
          "url": "https://www.checklist.design/?utm_source=tldrdesign",
          "reading_time_minutes": null,
          "source_domain": "checklist.design",
          "content_type": "tool",
          "is_sponsor": false
        },
        {
          "id": "tldr-design:2023-12-19:a12",
          "order": 2,
          "title": "IDENTIFY DESIGN ISSUES AND FIX THEM INSTANTLY",
          "summary": "Roast for Figma lets you easily clean up an old or imported file, remix a community resource, or update all tokens to a current library.",
          "url": "https://www.roastdesign.com/?utm_source=tldrdesign",
          "reading_time_minutes": null,
          "source_domain": "roastdesign.com",
          "content_type": "tool",
          "is_sponsor": false
        },
        {
          "id": "tldr-design:2023-12-19:a13",
          "order": 3,
          "title": "EASILY IMPORT YOUR VARIABLES FROM FIGMA TO WEBFLOW (WEBFLOW PLUGIN)",
          "summary": "The Figma to Webflow plugin allows you to import and sync your Figma variables and their associated values easily into Webflow.",
          "url": "https://webflow.com/apps/detail/figma-to-webflow?utm_source=tldrdesign",
          "reading_time_minutes": null,
          "source_domain": "webflow.com",
          "content_type": "editorial",
          "is_sponsor": false
        }
      ]
    },
    {
      "id": "miscellaneous",
      "heading": "MISCELLANEOUS",
      "order": 4,
      "articles": [
        {
          "id": "tldr-design:2023-12-19:a14",
          "order": 1,
          "title": "AN EXPLORATION IN COLLECTIVE INTERFACES",
          "summary": "The history of computing has been marked by its personal nature for the last 40 years, even though highly collaborative intentions marked the inception of digital interfaces. Researchers are now exploring interaction and interface design patterns for real-life collaboration.",
          "url": "https://uxdesign.cc/an-exploration-in-collective-interfaces-adbdbb7380e1?utm_source=tldrdesign",
          "reading_time_minutes": 8,
          "source_domain": "uxdesign.cc",
          "content_type": "editorial",
          "is_sponsor": false
        },
        {
          "id": "tldr-design:2023-12-19:a15",
          "order": 2,
          "title": "BEST DESIGNS AND DESIGNERS OF 2023: ‘A CHUNK OF GLOSSY SEXINESS’",
          "summary": "From 3D-printed headphones to a museum dedicated to crabs, The Guardian's panel of experts picks the designs and designers of the year.",
          "url": "https://www.theguardian.com/artanddesign/2023/dec/13/best-designs-and-designers-of-2023-a-chunk-of-glossy-sexiness?utm_source=tldrdesign",
          "reading_time_minutes": 11,
          "source_domain": "theguardian.com",
          "content_type": "editorial",
          "is_sponsor": false
        }
      ]
    },
    {
      "id": "quick-links",
      "heading": "QUICK LINKS",
      "order": 5,
      "articles": [
        {
          "id": "tldr-design:2023-12-19:a16",
          "order": 1,
          "title": "FIVE TIMES ARTISTS SUBVERTED THE CHRISTMAS TREE",
          "summary": "Christmas trees have become symbols of warmth and joy synonymous with the holiday spirit. However, the holiday season can also be a time of defiance and creativity, as evidenced by these examples of contemporary artists reinventing the iconic symbol.",
          "url": "https://somethingcurated.com/2023/12/15/5-times-artists-subverted-the-christmas-tree/?utm_source=tldrdesign",
          "reading_time_minutes": 3,
          "source_domain": "somethingcurated.com",
          "content_type": "editorial",
          "is_sponsor": false
        },
        {
          "id": "tldr-design:2023-12-19:a17",
          "order": 2,
          "title": "WHAT I’D PUT IN AN INTERFACE DESIGN MUSEUM",
          "summary": "Douglas Engelbart’s demo about the future of interfaces, the introduction of the iPhone’s multi-touch screen, the evolution of the Photoshop tool palette, the Web Design Manifesto 2012 by Jeffrey Zeldman, the original Apple Human Interface Guidelines, and the 37Better Project.",
          "url": "https://anthonyhobday.com/blog/20231216.html?utm_source=tldrdesign",
          "reading_time_minutes": 1,
          "source_domain": "anthonyhobday.com",
          "content_type": "editorial",
          "is_sponsor": false
        },
        {
          "id": "tldr-design:2023-12-19:a18",
          "order": 3,
          "title": "YOUR REFERRAL LINK - https://tldr.tech/design?ref=2613930",
          "summary": "",
          "url": "https://tldr.tech/design?ref=2613930",
          "reading_time_minutes": null,
          "source_domain": "tldr.tech",
          "content_type": "editorial",
          "is_sponsor": false
        }
      ]
    }
  ]
}
